README.rst
setup.cfg
setup.py
Jools.egg-info/PKG-INFO
Jools.egg-info/SOURCES.txt
Jools.egg-info/dependency_links.txt
Jools.egg-info/top_level.txt
jools/datetime/__init__.py